Lab02/src/sum1bit.v
module sum1b (
    input  a,
    input  b,
    input  ci,
    output  s,
    output co
);

wire xor1;
wire and1;
wire and2;

assign xor1 = a ^ b;
assign and1 = xor1 & ci;
assign and2 = a & b;
assign s = xor1 ^ ci;
assign co = and1 | and2;


endmodule

Lab02/src/sum4bit.v
`include "sum1bit/sum1bit.v"

module sum4b(A, B, Ci, S, Co);


input [3:0] A;
input [3:0] B;
input Ci;
output [3:0] S;   
output Co;

wire C1;
wire C2;
wire C3;


sum1b sum0(.a(A[0]), .b(B[0]), .ci(1'b1), .s(S[0]), .co(C1));
sum1b sum1(.a(A[1]), .b(B[1]), .ci(C1), .s(S[1]), .co(C2));
sum1b sum2(.a(A[2]), .b(B[2]), .ci(C2), .s(S[2]), .co(C3));
sum1b sum3(.a(A[3]), .b(B[3]), .ci(C3), .s(S[3]), .co(Co));


endmodule

Lab02/src/sum4bit_tb.v
// TESTBENCH

`include "sum4bit.v" // Instanciación del archivo a simular.
`timescale 1ps/1ps  // Declaración de escala de tiempo.

// Declaración de variables de entrada y cables de salida para el sumador.

module sum4b_tb();

    reg [3:0] A_tb;
    reg [3:0] B_tb;
    reg Ci_tb;

    wire [3:0] S_tb;
    wire Co_tb;

    sum4b uut(
        .A(A_tb),
        .B(B_tb),
        .Ci(Ci_tb),
        .S(S_tb),
        .Co(Co_tb)
    );

    // Inicialización de estados de entradas por tiempo.

    initial begin
        // Combinación 1
        Ci_tb = 0;
        A_tb = 4'b0000;
        B_tb = 4'b0000;
        #100; // Espera de 100ps

        // Combinación 2
        Ci_tb = 0;
        A_tb = 4'b0001;
        B_tb = 4'b0001;
        #100; // Espera de 100ps

        // Combinación 3
        Ci_tb = 0;
        A_tb = 4'b0010;
        B_tb = 4'b0010;
        #100; // Espera de 100ps

        // Combinación 4
        Ci_tb = 1;
        A_tb = 4'b0011;
        B_tb = 4'b0011;
        #100; // Espera de 100ps

        // Combinación 5
        Ci_tb = 1;
        A_tb = 4'b0100;
        B_tb = 4'b0100;
        #100; // Espera de 100ps

        // Combinación 6
        Ci_tb = 0;
        A_tb = 4'b0101;
        B_tb = 4'b0101;
        #100; // Espera de 100ps

        // Combinación 7
        Ci_tb = 0;
        A_tb = 4'b0110;
        B_tb = 4'b0110;
        #100; // Espera de 100ps

        // Combinación 8
        Ci_tb = 1;
        A_tb = 4'b0111;
        B_tb = 4'b0111;
        #100; // Espera de 100ps

        // Combinación 9
        Ci_tb = 1;
        A_tb = 4'b1000;
        B_tb = 4'b1000;
        #100; // Espera de 100ps

        // Combinación 10
        Ci_tb = 0;
        A_tb = 4'b1001;
        B_tb = 4'b1001;
        #100; // Espera de 100ps

        // Combinación 11
        Ci_tb = 0;
        A_tb = 4'b1010;
        B_tb = 4'b1010;
        #100; // Espera de 100ps

        // Combinación 12
        Ci_tb = 1;
        A_tb = 4'b1011;
        B_tb = 4'b1011;
        #100; // Espera de 100ps

        // Combinación 13
        Ci_tb = 1;
        A_tb = 4'b1100;
        B_tb = 4'b1100;
        #100; // Espera de 100ps

        // Combinación 14
        Ci_tb = 0;
        A_tb = 4'b1101;
        B_tb = 4'b1101;
        #100; // Espera de 100ps

        // Combinación 15
        Ci_tb = 0;
        A_tb = 4'b1110;
        B_tb = 4'b1110;
        #100; // Espera de 100ps

        // Combinación 16
        Ci_tb = 1;
        A_tb = 4'b1111;
        B_tb = 4'b1111;
        
    end
        
        /*
        Si necesitaramos mostrar todas las posibles combinaciones sería util usar el siguiente bloque de código en lugar del anterior:
            initial begin
                for (integer i = 0; i < 2; i = i + 1) begin
                    for (integer j = 0; j < 16; j = j + 1) begin
                        for (integer k = 0; k < 16; k = k + 1) begin
                            Ci_tb = i;
                            A_tb = j;
                            B_tb = k;
                            #100; // 100ps de paso de tiempo para cambio de estado.
                            count = count + 1;
                        end
                    end
                end
            end        
        */



    // Salida del archivo '.vcd' y sus parámetros para la simulación.
    
    initial begin
        $dumpfile("sum4b.vcd");
        $dumpvars(0, uut);
        #1600 $finish; // Tiempo total de simulación (16 * 100ps = 1600ps)
    end

endmodule

Lab02/src/sum4b.vcd
$date
	Sat Jul 27 19:19:12 2024
$end
$version
	Icarus Verilog
$end
$timescale
	1ps
$end
$scope module sum4b_tb $end
$scope module uut $end
$var wire 4 ! A [3:0] $end
$var wire 4 " B [3:0] $end
$var wire 1 # Ci $end
$var wire 4 $ S [3:0] $end
$var wire 1 % Co $end
$var wire 1 & C3 $end
$var wire 1 ' C2 $end
$var wire 1 ( C1 $end
$scope module sum0 $end
$var wire 1 ) a $end
$var wire 1 * and1 $end
$var wire 1 + and2 $end
$var wire 1 , b $end
$var wire 1 - ci $end
$var wire 1 ( co $end
$var wire 1 . s $end
$var wire 1 / xor1 $end
$upscope $end
$scope module sum1 $end
$var wire 1 0 a $end
$var wire 1 1 and1 $end
$var wire 1 2 and2 $end
$var wire 1 3 b $end
$var wire 1 ( ci $end
$var wire 1 ' co $end
$var wire 1 4 s $end
$var wire 1 5 xor1 $end
$upscope $end
$scope module sum2 $end
$var wire 1 6 a $end
$var wire 1 7 and1 $end
$var wire 1 8 and2 $end
$var wire 1 9 b $end
$var wire 1 ' ci $end
$var wire 1 & co $end
$var wire 1 : s $end
$var wire 1 ; xor1 $end
$upscope $end
$scope module sum3 $end
$var wire 1 < a $end
$var wire 1 = and1 $end
$var wire 1 > and2 $end
$var wire 1 ? b $end
$var wire 1 & ci $end
$var wire 1 % co $end
$var wire 1 @ s $end
$var wire 1 A xor1 $end
$upscope $end
$upscope $end
$upscope $end
$enddefinitions $end
$comment Show the parameter values. $end
$dumpall
$end
#0
$dumpvars
0A
0@
0?
0>
0=
0<
0;
0:
09
08
07
06
05
04
03
02
01
00
0/
1.
1-
0,
0+
0*
0)
0(
0'
0&
0%
b1 $
0#
b0 "
b0 !
$end
#100
b11 $
14
1(
1+
1,
1)
b1 "
b1 !
#200
04
b101 $
1:
0(
1'
0+
12
0,
13
0)
10
b10 "
b10 !
#300
b111 $
14
1(
1+
1,
1)
b11 "
b11 !
1#
#400
04
0:
b1001 $
1@
0(
0'
1&
0+
02
18
0,
03
19
0)
00
16
b100 "
b100 !
#500
b1011 $
14
1(
1+
1,
1)
b101 "
b101 !
0#
#600
04
b1101 $
1:
0(
1'
0+
12
0,
13
0)
10
b110 "
b110 !
#700
b1111 $
14
1(
1+
1,
1)
b111 "
b111 !
1#
#800
04
0:
b1 $
0@
0(
0'
0&
1%
0+
02
08
1>
0,
03
09
1?
0)
00
06
1<
b1000 "
b1000 !
#900
b11 $
14
1(
1+
1,
1)
b1001 "
b1001 !
0#
#1000
04
b101 $
1:
0(
1'
0+
12
0,
13
0)
10
b1010 "
b1010 !
#1100
b111 $
14
1(
1+
1,
1)
b1011 "
b1011 !
1#
#1200
04
0:
b1001 $
1@
0(
0'
1&
0+
02
18
0,
03
19
0)
00
16
b1100 "
b1100 !
#1300
b1011 $
14
1(
1+
1,
1)
b1101 "
b1101 !
0#
#1400
04
b1101 $
1:
0(
1'
0+
12
0,
13
0)
10
b1110 "
b1110 !
#1500
b1111 $
14
1(
1+
1,
1)
b1111 "
b1111 !
1#
