Proyecto/src/Motor/Motor.v
`timescale 1ns / 1ps

// Módulo para el control de motores
module Motor (
    input wire clk,                // Reloj del sistema
    input wire reset,              // Señal de reset asíncrono
    input wire [1:0] cmd,          // Comando recibido desde House.v (2 bits)
    input wire TopeA,              // Tope superior (pulsador)
    input wire TopeB,              // Tope inferior (pulsador)
    output reg motor_up,           // Control de motor hacia arriba
    output reg motor_down,         // Control de motor hacia abajo
    output reg TopeA_S,            // Señal de tope superior (activada cuando TopeA es presionado)
    output reg TopeB_S             // Señal de tope inferior (activada cuando TopeB es presionado)
);

    // Proceso principal del módulo
    always @(posedge clk or posedge reset) begin
        if (reset) begin
            // Resetear salidas
            motor_up <= 0;
            motor_down <= 0;
            TopeA_S <= 0;
            TopeB_S <= 0;
        end else begin
            // Actualizar las señales de tope según las entradas
            TopeA_S <= TopeA; // Activar señal de tope superior si TopeA es presionado
            TopeB_S <= TopeB; // Activar señal de tope inferior si TopeB es presionado

            // Comprobar comando
            case (cmd)
                2'b01: begin // Comando para subir
                    if (!TopeA) begin // Si no está en el tope superior
                        motor_up <= 1;  // Activar motor hacia arriba
                        motor_down <= 0; // Desactivar motor hacia abajo
                    end else begin
                        motor_up <= 0;   // Detener motor hacia arriba
                    end
                end
                2'b10: begin // Comando para bajar
                    if (!TopeB) begin // Si no está en el tope inferior
                        motor_down <= 1; // Activar motor hacia abajo
                        motor_up <= 0;   // Desactivar motor hacia arriba
                    end else begin
                        motor_down <= 0; // Detener motor hacia abajo
                    end
                end
                default: begin // Comando no válido
                    motor_up <= 0;     // Detener motor hacia arriba
                    motor_down <= 0;   // Detener motor hacia abajo
                end
            endcase
        end
    end
endmodule

Proyecto/src/Motor/Motor_tb.v
`timescale 1ns / 1ps

`include "Motor.v"  // Incluir el módulo de motores

module Motor_tb;

    // Declaración de señales de prueba
    reg clk;              // Reloj del sistema
    reg reset;            // Señal de reset asíncrono
    reg [1:0] cmd;        // Comando a enviar (2 bits para comandos 1 y 2)
    reg TopeA;            // Tope superior
    reg TopeB;            // Tope inferior
    wire motor_up;        // Salida de control de motor hacia arriba
    wire motor_down;      // Salida de control de motor hacia abajo
    wire TopeA_S;         // Señal de tope superior
    wire TopeB_S;         // Señal de tope inferior

    // Instanciar el módulo de motores
    Motor uut (
        .clk(clk),
        .reset(reset),
        .cmd(cmd),
        .TopeA(TopeA),
        .TopeB(TopeB),
        .motor_up(motor_up),
        .motor_down(motor_down),
        .TopeA_S(TopeA_S),
        .TopeB_S(TopeB_S)
    );

    // Generación de reloj
    initial begin
        clk = 0;
        forever #10 clk = ~clk;  // Cambiar estado cada 10 ns (50 MHz)
    end

    // Inicializar señales y realizar la simulación
    initial begin
        // Inicialización
        reset = 1;       // Activar reset
        cmd = 2'b00;     // Comando inicial (ninguno)
        TopeA = 0;       // Tope superior no activado
        TopeB = 0;       // Tope inferior no activado

        // Esperar un tiempo
        #20;
        reset = 0;       // Desactivar reset

        // Prueba de subir motor
        #20;
        cmd = 2'b01;     // Comando para subir
        #40;             // Esperar tiempo de activación
        TopeA = 0;       // Asegurarse de que el tope no está activado

        // Prueba de bajar motor
        #20;
        cmd = 2'b10;     // Comando para bajar
        #40;             // Esperar tiempo de activación
        TopeB = 0;       // Asegurarse de que el tope no está activado

        // Desactivación de comandos
        #20;
        cmd = 2'b00;     // Comando no válido

        // Activar topes
        #20;
        TopeA = 1;       // Activar tope superior
        #20;
        TopeB = 1;       // Activar tope inferior

        // Prueba cruzada: comando 1 con TopeA activado
        #20;
        cmd = 2'b01;     // Comando para subir
        TopeA = 1;       // Activar tope superior
        #40;             // Esperar tiempo de activación

        // Prueba cruzada: comando 2 con TopeB activado
        #20;
        cmd = 2'b10;     // Comando para bajar
        TopeB = 1;       // Activar tope inferior
        #40;             // Esperar tiempo de activación

        // Finalizar la simulación
        #20;
        $finish;
    end

    // Generación del archivo VCD para visualizar en GTKWave
    initial begin
        $dumpfile("Motor_tb.vcd");
        $dumpvars(0, Motor_tb);
    end
endmodule

Proyecto/src/Motor/Motor_tb.vcd
$date
	Tue Sep 24 09:07:07 2024
$end
$version
	Icarus Verilog
$end
$timescale
	1ps
$end
$scope module Motor_tb $end
$var wire 1 ! motor_up $end
$var wire 1 " motor_down $end
$var wire 1 # TopeB_S $end
$var wire 1 $ TopeA_S $end
$var reg 1 % TopeA $end
$var reg 1 & TopeB $end
$var reg 1 ' clk $end
$var reg 2 ( cmd [1:0] $end
$var reg 1 ) reset $end
$scope module uut $end
$var wire 1 % TopeA $end
$var wire 1 & TopeB $end
$var wire 1 ' clk $end
$var wire 2 * cmd [1:0] $end
$var wire 1 ) reset $end
$var reg 1 $ TopeA_S $end
$var reg 1 # TopeB_S $end
$var reg 1 " motor_down $end
$var reg 1 ! motor_up $end
$upscope $end
$upscope $end
$enddefinitions $end
$comment Show the parameter values. $end
$dumpall
$end
#0
$dumpvars
b0 *
1)
b0 (
0'
0&
0%
0$
0#
0"
0!
$end
#10000
1'
#20000
0'
0)
#30000
1'
#40000
0'
b1 (
b1 *
#50000
1!
1'
#60000
0'
#70000
1'
#80000
0'
#90000
1'
#100000
0'
b10 (
b10 *
#110000
0!
1"
1'
#120000
0'
#130000
1'
#140000
0'
#150000
1'
#160000
0'
b0 (
b0 *
#170000
0"
1'
#180000
0'
1%
#190000
1$
1'
#200000
0'
1&
#210000
1#
1'
#220000
0'
b1 (
b1 *
#230000
1'
#240000
0'
#250000
1'
#260000
0'
#270000
1'
#280000
0'
b10 (
b10 *
