Lab01/src/02/compuertas2.v
module compuertas2(

    //Entradas de las diferentes compuertas y entradas del sistema
    input A,
    input B, 
    input C,

    //Salidas de las compuertas y del sistema, C0 pertence a Co
    output S1,
    output C0
    );

    //Asiganmos los valores teniendo en cuenta que creamos una igualdad para dos variables
    //representan una salida y una entrada de una compuerta

    assign S1 = (A^B)^C;
    assign C0 = ((A^B)&C)|(A&B);


endmodule

Lab01/src/02/compuertas2_tb.v
//  TESTBENCH

`include "compuertas2.v" //Inclusión del archivo a simular.
`timescale 1ps/1ps  //Declaración de escala de tiempo.


module compuertas2_tb ();
    //Declaración de variables de entrada para las compuertas.

    reg A_tb;
    reg B_tb;
    reg C_tb;

    //Declaración de cables como salidas para las compuertas.
    wire S1_tb;
    wire C0_tb;


    //Instalacion del archivo principal.

    compuertas2 uut(
        .A(A_tb),
        .B(B_tb),
        .C(C_tb),
        .S1(S1_tb),
        .C0(C0_tb)
    );

    //Inicialización de estados por tiempo para las entradas.

    initial begin
        A_tb = 0; 
        B_tb = 0;
        C_tb = 0;
        #100    //100ps de paso de tiempo para cambio de estado.
        A_tb = 0; 
        B_tb = 0;
        C_tb = 1;
        #100    //100ps de paso de tiempo para cambio de estado.
        A_tb = 0; 
        B_tb = 1;
        C_tb = 0;
        #100    //100ps de paso de tiempo para cambio de estado.
        A_tb = 0; 
        B_tb = 1;
        C_tb = 1;
        #100    //100ps de paso de tiempo para cambio de estado.
        A_tb = 1; 
        B_tb = 0;
        C_tb = 0;
        #100    //100ps de paso de tiempo para cambio de estado.
        A_tb = 1; 
        B_tb = 0;
        C_tb = 1;
        #100    //100ps de paso de tiempo para cambio de estado.
        A_tb = 1; 
        B_tb = 1;
        C_tb = 0;
        #100    //100ps de paso de tiempo para cambio de estado.
        A_tb = 1; 
        B_tb = 1;
        C_tb = 1;
    end

    //Salida del archivo '.vcd' y sus parametros para la simulación.
    initial begin
        $dumpfile("compuertas2.vcd");
        $dumpvars(-1, uut);
        #800 $finish;
    end

endmodule

Lab01/src/02/build/compuertas2.vcd
$date
	Sat Jul 27 17:24:58 2024
$end
$version
	Icarus Verilog
$end
$timescale
	1ps
$end
$scope module compuertas2_tb $end
$scope module uut $end
$var wire 1 ! A $end
$var wire 1 " B $end
$var wire 1 # C $end
$var wire 1 $ C0 $end
$var wire 1 % S1 $end
$upscope $end
$upscope $end
$enddefinitions $end
$comment Show the parameter values. $end
$dumpall
$end
#0
$dumpvars
0%
0$
0#
0"
0!
$end
#100
1%
1#
#200
0#
1"
#300
1$
0%
1#
#400
0$
1%
0#
0"
1!
#500
1$
0%
1#
#600
0#
1"
#700
1%
1#
