Lab02/src/sum1bit.v
module sum1b (
    input  a,
    input  b,
    input  ci,
    output  s,
    output co
);

wire xor1;
wire and1;
wire and2;

assign xor1 = a ^ b;
assign and1 = xor1 & ci;
assign and2 = a & b;
assign s = xor1 ^ ci;
assign co = and1 | and2;


endmodule

Lab02/src/sum1bit/sum1bit_tb.v
// TESTBENCH

`include "sum1bit.v" // Instanciación del archivo a simular.
`timescale 1ps/1ps  //Declaración escala de tiempo.

//Declaración variables de entrada y cables de salida para el sumador.

module sum1bit_tb ();

    reg a_tb;
    reg b_tb;
    reg ci_tb;

    wire s_tb;
    wire co_tb;

    sum1b uut(
        .a(a_tb),
        .b(b_tb),
        .ci(ci_tb),
        .s(s_tb),
        .co(co_tb)

    );

    // Inicialización de estados de entradas por tiempo.

    initial begin

        a_tb = 0;
        b_tb = 0;
        ci_tb = 0;   

        #100    //100ps de paso de tiempo para cambio de estado.

        a_tb = 0;
        b_tb = 1;
        ci_tb = 0;   

        #100    //100ps de paso de tiempo para cambio de estado.

        a_tb = 1;
        b_tb = 0;
        ci_tb = 0;   

        #100    //100ps de paso de tiempo para cambio de estado.

        a_tb = 1;
        b_tb = 1;
        ci_tb = 0;   

        #100    //100ps de paso de tiempo para cambio de estado.

        a_tb = 0;
        b_tb = 0;
        ci_tb = 1;   

        #100    //100ps de paso de tiempo para cambio de estado.

        a_tb = 0;
        b_tb = 1;
        ci_tb = 1;   

        #100    //100ps de paso de tiempo para cambio de estado.

        a_tb = 1;
        b_tb = 0;
        ci_tb = 1;   

        #100    //100ps de paso de tiempo para cambio de estado.

        a_tb = 1;
        b_tb = 1;
        ci_tb = 1;   


    end
        
    //Salida del archivo '.vcd' y sus parametros para la simulación.
    
    initial begin
        $dumpfile("sum1bit.vcd");
        $dumpvars(0, uut);
        #800 $finish;
    end

endmodule

Lab02/src/sum1bit/sum1bit.vcd
$date
	Sat Jul 27 18:50:58 2024
$end
$version
	Icarus Verilog
$end
$timescale
	1ps
$end
$scope module sum1bit_tb $end
$scope module uut $end
$var wire 1 ! a $end
$var wire 1 " and1 $end
$var wire 1 # and2 $end
$var wire 1 $ b $end
$var wire 1 % ci $end
$var wire 1 & co $end
$var wire 1 ' s $end
$var wire 1 ( xor1 $end
$upscope $end
$upscope $end
$enddefinitions $end
$comment Show the parameter values. $end
$dumpall
$end
#0
$dumpvars
0(
0'
0&
0%
0$
0#
0"
0!
$end
#100
1'
1(
1$
#200
0$
1!
#300
0'
1&
0(
1#
1$
#400
0&
1'
0#
1%
0$
0!
#500
1&
1"
0'
1(
1$
#600
0$
1!
#700
0"
1'
0(
1#
1$
