Proyecto/src/Leds/Leds.v
`timescale 1ns / 1ps

// Módulo para controlar LEDs
module Leds (
    input wire clk,              // Reloj del sistema
    input wire reset,            // Señal de reset asíncrono
    input wire [2:0] cmd,        // Comando para encender LEDs individuales
    output reg [2:0] leds        // Salida para los LEDs
);

    // Parámetros
    parameter CLK_FREQ = 50000000; // Frecuencia del reloj en Hz
    parameter LED_TOGGLE_TIME = 30; // Tiempo en segundos para cambiar el estado de los LEDs
    localparam COUNT_MAX = CLK_FREQ * LED_TOGGLE_TIME; // Contador para 30 segundos

    reg [31:0] counter;           // Contador para medir el tiempo
    reg toggle;                   // Señal para indicar el cambio de estado

    // Proceso principal del módulo
    always @(posedge clk or posedge reset) begin
        if (reset) begin
            leds <= 3'b000;         // Apagar todos los LEDs en reset
            counter <= 0;           // Reiniciar contador
            toggle <= 0;            // Inicializar señal de toggle
        end else begin
            // Contador para el tiempo de togglear LEDs
            if (counter < COUNT_MAX - 1) begin
                counter <= counter + 1; // Incrementar contador
            end else begin
                counter <= 0;           // Reiniciar contador
                toggle <= ~toggle;      // Invertir la señal de toggle
            end
            
            // Lógica para controlar el estado de los LEDs
            if (toggle) begin
                leds <= 3'b111;         // Encender todos los LEDs
            end else begin
                leds <= 3'b000;         // Apagar todos los LEDs
            end
            
            // Control de LEDs individuales
            if (cmd) begin
                leds <= cmd;            // Encender LEDs individuales según el comando
            end
        end
    end
endmodule

Proyecto/src/Leds/Leds-tb.v
`timescale 1ns / 1ps

// Incluir el módulo Leds
`include "Leds.v"

// Testbench para el módulo Leds
module Leds_tb;

    // Parámetros
    parameter CLK_PERIOD = 20; // Período del reloj en ns (50MHz)

    // Señales de prueba
    reg clk;                     // Señal de reloj
    reg reset;                   // Señal de reset
    reg [2:0] cmd;              // Comando para encender LEDs individuales
    wire [2:0] leds;            // Salida de los LEDs

    // Instanciar el módulo Leds
    Leds leds_inst (
        .clk(clk),
        .reset(reset),
        .cmd(cmd),
        .leds(leds)               // Asegúrate que este nombre coincida con el módulo
    );

    // Generar señal de reloj
    initial begin
        clk = 0;
        forever #(CLK_PERIOD / 2) clk = ~clk; // Cambiar el estado del reloj
    end

    // Proceso de prueba
    initial begin
        // Inicializar señales
        reset = 1;       // Activa el reset
        cmd = 3'b000;    // Inicializar comando
        #(CLK_PERIOD);   // Esperar un ciclo de reloj
        reset = 0;       // Desactivar el reset

        // Simulación del control de LEDs
        #(CLK_PERIOD * 5); // Esperar 5 ciclos de reloj

        // Activar comando para encender el LED 1
        cmd = 3'b001;      // Encender LED 1
        #(CLK_PERIOD * 30); // Esperar 30 ciclos de reloj

        // Activar comando para encender el LED 2
        cmd = 3'b010;      // Encender LED 2
        #(CLK_PERIOD * 30); // Esperar 30 ciclos de reloj

        // Activar comando para encender el LED 3
        cmd = 3'b100;      // Encender LED 3
        #(CLK_PERIOD * 30); // Esperar 30 ciclos de reloj

        // Dejar que el temporizador automático opere
        #(CLK_PERIOD * 60); // Esperar para observar el modo automático

        // Finalizar simulación
        $finish;
    end

    // Generar archivo .vcd para GTKWave
    initial begin
        $dumpfile("Leds_tb.vcd"); // Nombre del archivo .vcd
        $dumpvars(0, Leds_tb);     // Registrar todas las variables del testbench
    end
endmodule

Proyecto/src/Leds/Leds_tb.vcd
$date
	Tue Sep 24 09:55:26 2024
$end
$version
	Icarus Verilog
$end
$timescale
	1ps
$end
$scope module Leds_tb $end
$var wire 3 ! leds [2:0] $end
$var parameter 32 " CLK_PERIOD $end
$var reg 1 # clk $end
$var reg 3 $ cmd [2:0] $end
$var reg 1 % reset $end
$scope module leds_inst $end
$var wire 1 # clk $end
$var wire 3 & cmd [2:0] $end
$var wire 1 % reset $end
$var parameter 32 ' CLK_FREQ $end
$var parameter 64 ( COUNT_MAX $end
$var parameter 32 ) LED_TOGGLE_TIME $end
$var reg 32 * counter [31:0] $end
$var reg 3 + leds [2:0] $end
$var reg 1 , toggle $end
$upscope $end
$upscope $end
$enddefinitions $end
$comment Show the parameter values. $end
$dumpall
b11110 )
b1011001011010000010111100000000 (
b10111110101111000010000000 '
b10100 "
$end
#0
$dumpvars
0,
b0 +
b0 *
b0 &
1%
b0 $
0#
b0 !
$end
#10000
1#
#20000
0#
0%
#30000
b1 *
1#
#40000
0#
#50000
b10 *
1#
#60000
0#
#70000
b11 *
1#
#80000
0#
#90000
b100 *
1#
#100000
0#
#110000
b101 *
1#
#120000
0#
b1 $
b1 &
#130000
b1 !
b1 +
b110 *
1#
#140000
0#
#150000
b1 !
b1 +
b111 *
1#
#160000
0#
#170000
b1 !
b1 +
b1000 *
1#
#180000
0#
#190000
b1 !
b1 +
b1001 *
1#
#200000
0#
#210000
b1 !
b1 +
b1010 *
1#
#220000
0#
#230000
b1 !
b1 +
b1011 *
1#
#240000
0#
#250000
b1 !
b1 +
b1100 *
1#
#260000
0#
#270000
b1 !
b1 +
b1101 *
1#
#280000
0#
#290000
b1 !
b1 +
b1110 *
1#
#300000
0#
#310000
b1 !
b1 +
b1111 *
1#
#320000
0#
#330000
b1 !
b1 +
b10000 *
1#
#340000
0#
#350000
b1 !
b1 +
b10001 *
1#
#360000
0#
#370000
b1 !
b1 +
b10010 *
1#
#380000
0#
#390000
b1 !
b1 +
b10011 *
1#
#400000
0#
#410000
b1 !
b1 +
b10100 *
1#
#420000
0#
#430000
b1 !
b1 +
b10101 *
1#
#440000
0#
#450000
b1 !
b1 +
b10110 *
1#
#460000
0#
#470000
b1 !
b1 +
b10111 *
1#
#480000
0#
#490000
b1 !
b1 +
b11000 *
1#
#500000
0#
#510000
b1 !
b1 +
b11001 *
1#
#520000
0#
#530000
b1 !
b1 +
b11010 *
1#
#540000
0#
#550000
b1 !
b1 +
b11011 *
1#
#560000
0#
#570000
b1 !
b1 +
b11100 *
1#
#580000
0#
#590000
b1 !
b1 +
b11101 *
1#
#600000
0#
#610000
b1 !
b1 +
b11110 *
1#
#620000
0#
#630000
b1 !
b1 +
b11111 *
1#
#640000
0#
#650000
b1 !
b1 +
b100000 *
1#
#660000
0#
#670000
b1 !
b1 +
b100001 *
1#
#680000
0#
#690000
b1 !
b1 +
b100010 *
1#
#700000
0#
#710000
b1 !
b1 +
b100011 *
1#
#720000
0#
b10 $
b10 &
#730000
b10 !
b10 +
b100100 *
1#
#740000
0#
#750000
b10 !
b10 +
b100101 *
1#
#760000
0#
#770000
b10 !
b10 +
b100110 *
1#
#780000
0#
#790000
b10 !
b10 +
b100111 *
1#
#800000
0#
#810000
b10 !
b10 +
b101000 *
1#
#820000
0#
#830000
b10 !
b10 +
b101001 *
1#
#840000
0#
#850000
b10 !
b10 +
b101010 *
1#
#860000
0#
#870000
b10 !
b10 +
b101011 *
1#
#880000
0#
#890000
b10 !
b10 +
b101100 *
1#
#900000
0#
#910000
b10 !
b10 +
b101101 *
1#
#920000
0#
#930000
b10 !
b10 +
b101110 *
1#
#940000
0#
#950000
b10 !
b10 +
b101111 *
1#
#960000
0#
#970000
b10 !
b10 +
b110000 *
1#
#980000
0#
#990000
b10 !
b10 +
b110001 *
1#
#1000000
0#
#1010000
b10 !
b10 +
b110010 *
1#
#1020000
0#
#1030000
b10 !
b10 +
b110011 *
1#
#1040000
0#
#1050000
b10 !
b10 +
b110100 *
1#
#1060000
0#
#1070000
b10 !
b10 +
b110101 *
1#
#1080000
0#
#1090000
b10 !
b10 +
b110110 *
1#
#1100000
0#
#1110000
b10 !
b10 +
b110111 *
1#
#1120000
0#
#1130000
b10 !
b10 +
b111000 *
1#
#1140000
0#
#1150000
b10 !
b10 +
b111001 *
1#
#1160000
0#
#1170000
b10 !
b10 +
b111010 *
1#
#1180000
0#
#1190000
b10 !
b10 +
b111011 *
1#
#1200000
0#
#1210000
b10 !
b10 +
b111100 *
1#
#1220000
0#
#1230000
b10 !
b10 +
b111101 *
1#
#1240000
0#
#1250000
b10 !
b10 +
b111110 *
1#
#1260000
0#
#1270000
b10 !
b10 +
b111111 *
1#
#1280000
0#
#1290000
b10 !
b10 +
b1000000 *
1#
#1300000
0#
#1310000
b10 !
b10 +
b1000001 *
1#
#1320000
0#
b100 $
b100 &
#1330000
b100 !
b100 +
b1000010 *
1#
#1340000
0#
#1350000
b100 !
b100 +
b1000011 *
1#
#1360000
0#
#1370000
b100 !
b100 +
b1000100 *
1#
#1380000
0#
#1390000
b100 !
b100 +
b1000101 *
1#
#1400000
0#
#1410000
b100 !
b100 +
b1000110 *
1#
#1420000
0#
#1430000
b100 !
b100 +
b1000111 *
1#
#1440000
0#
#1450000
b100 !
b100 +
b1001000 *
1#
#1460000
0#
#1470000
b100 !
b100 +
b1001001 *
1#
#1480000
0#
#1490000
b100 !
b100 +
b1001010 *
1#
#1500000
0#
#1510000
b100 !
b100 +
b1001011 *
1#
#1520000
0#
#1530000
b100 !
b100 +
b1001100 *
1#
#1540000
0#
#1550000
b100 !
b100 +
b1001101 *
1#
#1560000
0#
#1570000
b100 !
b100 +
b1001110 *
1#
#1580000
0#
#1590000
b100 !
b100 +
b1001111 *
1#
#1600000
0#
#1610000
b100 !
b100 +
b1010000 *
1#
#1620000
0#
#1630000
b100 !
b100 +
b1010001 *
1#
#1640000
0#
#1650000
b100 !
b100 +
b1010010 *
1#
#1660000
0#
#1670000
b100 !
b100 +
b1010011 *
1#
#1680000
0#
#1690000
b100 !
b100 +
b1010100 *
1#
#1700000
0#
#1710000
b100 !
b100 +
b1010101 *
1#
#1720000
0#
#1730000
b100 !
b100 +
b1010110 *
1#
#1740000
0#
#1750000
b100 !
b100 +
b1010111 *
1#
#1760000
0#
#1770000
b100 !
b100 +
b1011000 *
1#
#1780000
0#
#1790000
b100 !
b100 +
b1011001 *
1#
#1800000
0#
#1810000
b100 !
b100 +
b1011010 *
1#
#1820000
0#
#1830000
b100 !
b100 +
b1011011 *
1#
#1840000
0#
#1850000
b100 !
b100 +
b1011100 *
1#
#1860000
0#
#1870000
b100 !
b100 +
b1011101 *
1#
#1880000
0#
#1890000
b100 !
b100 +
b1011110 *
1#
#1900000
0#
#1910000
b100 !
b100 +
b1011111 *
1#
#1920000
0#
#1930000
b100 !
b100 +
b1100000 *
1#
#1940000
0#
#1950000
b100 !
b100 +
b1100001 *
1#
#1960000
0#
#1970000
b100 !
b100 +
b1100010 *
1#
#1980000
0#
#1990000
b100 !
b100 +
b1100011 *
1#
#2000000
0#
#2010000
b100 !
b100 +
b1100100 *
1#
#2020000
0#
#2030000
b100 !
b100 +
b1100101 *
1#
#2040000
0#
#2050000
b100 !
b100 +
b1100110 *
1#
#2060000
0#
#2070000
b100 !
b100 +
b1100111 *
1#
#2080000
0#
#2090000
b100 !
b100 +
b1101000 *
1#
#2100000
0#
#2110000
b100 !
b100 +
b1101001 *
1#
#2120000
0#
#2130000
b100 !
b100 +
b1101010 *
1#
#2140000
0#
#2150000
b100 !
b100 +
b1101011 *
1#
#2160000
0#
#2170000
b100 !
b100 +
b1101100 *
1#
#2180000
0#
#2190000
b100 !
b100 +
b1101101 *
1#
#2200000
0#
#2210000
b100 !
b100 +
b1101110 *
1#
#2220000
0#
#2230000
b100 !
b100 +
b1101111 *
1#
#2240000
0#
#2250000
b100 !
b100 +
b1110000 *
1#
#2260000
0#
#2270000
b100 !
b100 +
b1110001 *
1#
#2280000
0#
#2290000
b100 !
b100 +
b1110010 *
1#
#2300000
0#
#2310000
b100 !
b100 +
b1110011 *
1#
#2320000
0#
#2330000
b100 !
b100 +
b1110100 *
1#
#2340000
0#
#2350000
b100 !
b100 +
b1110101 *
1#
#2360000
0#
#2370000
b100 !
b100 +
b1110110 *
1#
#2380000
0#
#2390000
b100 !
b100 +
b1110111 *
1#
#2400000
0#
#2410000
b100 !
b100 +
b1111000 *
1#
#2420000
0#
#2430000
b100 !
b100 +
b1111001 *
1#
#2440000
0#
#2450000
b100 !
b100 +
b1111010 *
1#
#2460000
0#
#2470000
b100 !
b100 +
b1111011 *
1#
#2480000
0#
#2490000
b100 !
b100 +
b1111100 *
1#
#2500000
0#
#2510000
b100 !
b100 +
b1111101 *
1#
#2520000
0#
#2530000
b100 !
b100 +
b1111110 *
1#
#2540000
0#
#2550000
b100 !
b100 +
b1111111 *
1#
#2560000
0#
#2570000
b100 !
b100 +
b10000000 *
1#
#2580000
0#
#2590000
b100 !
b100 +
b10000001 *
1#
#2600000
0#
#2610000
b100 !
b100 +
b10000010 *
1#
#2620000
0#
#2630000
b100 !
b100 +
b10000011 *
1#
#2640000
0#
#2650000
b100 !
b100 +
b10000100 *
1#
#2660000
0#
#2670000
b100 !
b100 +
b10000101 *
1#
#2680000
0#
#2690000
b100 !
b100 +
b10000110 *
1#
#2700000
0#
#2710000
b100 !
b100 +
b10000111 *
1#
#2720000
0#
#2730000
b100 !
b100 +
b10001000 *
1#
#2740000
0#
#2750000
b100 !
b100 +
b10001001 *
1#
#2760000
0#
#2770000
b100 !
b100 +
b10001010 *
1#
#2780000
0#
#2790000
b100 !
b100 +
b10001011 *
1#
#2800000
0#
#2810000
b100 !
b100 +
b10001100 *
1#
#2820000
0#
#2830000
b100 !
b100 +
b10001101 *
1#
#2840000
0#
#2850000
b100 !
b100 +
b10001110 *
1#
#2860000
0#
#2870000
b100 !
b100 +
b10001111 *
1#
#2880000
0#
#2890000
b100 !
b100 +
b10010000 *
1#
#2900000
0#
#2910000
b100 !
b100 +
b10010001 *
1#
#2920000
0#
#2930000
b100 !
b100 +
b10010010 *
1#
#2940000
0#
#2950000
b100 !
b100 +
b10010011 *
1#
#2960000
0#
#2970000
b100 !
b100 +
b10010100 *
1#
#2980000
0#
#2990000
b100 !
b100 +
b10010101 *
1#
#3000000
0#
#3010000
b100 !
b100 +
b10010110 *
1#
#3020000
0#
#3030000
b100 !
b100 +
b10010111 *
1#
#3040000
0#
#3050000
b100 !
b100 +
b10011000 *
1#
#3060000
0#
#3070000
b100 !
b100 +
b10011001 *
1#
#3080000
0#
#3090000
b100 !
b100 +
b10011010 *
1#
#3100000
0#
#3110000
b100 !
b100 +
b10011011 *
1#
