Proyecto/src/BT/BTr.v
`timescale 1ns / 1ps

// Módulo para la recepción de datos a través de Bluetooth
module BTr (
    input wire clk,              // Reloj del sistema
    input wire reset,            // Señal de reset asíncrono
    input wire rx,               // Entrada de recepción (UART)
    output reg [7:0] data_out,   // Datos recibidos (8 bits)
    output reg ready             // Indica que los datos están listos
);

    // Parámetros de configuración
    parameter CLK_FREQ = 50000000; // Frecuencia del reloj del sistema en Hz
    parameter BAUD_RATE = 9600;    // Tasa de baudios para la comunicación UART

    // Calcular el contador de baudios con oversampling x16
    localparam BAUD_COUNT = (CLK_FREQ / (BAUD_RATE * 16)) - 1;

    // Registros internos
    reg [15:0] baud_counter;       // Contador para la generación del tiempo de baud
    reg [3:0] bit_index;           // Índice del bit actual recibido
    reg [7:0] data_reg;            // Registro para almacenar los datos recibidos
    reg [1:0] state;               // Estado actual del módulo

    // Definición de estados para la máquina de estados
    localparam IDLE = 2'b00,       // Estado de inactividad
               RECEIVE_START = 2'b01, // Esperando el bit de inicio
               RECEIVE_DATA = 2'b10,  // Recibiendo datos
               RECEIVE_STOP = 2'b11;  // Esperando el bit de parada

    // Proceso principal del módulo
    always @(posedge clk or posedge reset) begin
        if (reset) begin
            data_out <= 0;          // Reiniciar datos de salida
            ready <= 0;             // Indicar que los datos no están listos
            baud_counter <= 0;      // Reiniciar contador de baud
            bit_index <= 0;         // Reiniciar índice de bit
            state <= IDLE;          // Regresar al estado inicial
        end else begin
            case (state)
                IDLE: begin
                    if (rx == 0) begin  // Esperar a que rx baje a 0 (bit de inicio)
                        baud_counter <= 0; // Reiniciar contador de baud
                        state <= RECEIVE_START; // Cambiar al estado de espera de inicio
                    end
                end

                RECEIVE_START: begin
                    if (baud_counter < BAUD_COUNT) begin
                        baud_counter <= baud_counter + 1; // Contar hasta BAUD_COUNT
                    end else begin
                        baud_counter <= 0; // Reiniciar contador
                        state <= RECEIVE_DATA; // Cambiar al estado de recepción de datos
                        bit_index <= 0; // Reiniciar índice de bit
                    end
                end

                RECEIVE_DATA: begin
                    if (baud_counter < BAUD_COUNT) begin
                        baud_counter <= baud_counter + 1; // Contar hasta BAUD_COUNT
                    end else begin
                        baud_counter <= 0; // Reiniciar contador
                        data_reg[bit_index] <= rx; // Recibir el siguiente bit
                        if (bit_index < 7) begin
                            bit_index <= bit_index + 1; // Siguiente bit
                        end else begin
                            state <= RECEIVE_STOP; // Cambiar al estado de espera de parada
                        end
                    end
                end

                RECEIVE_STOP: begin
                    if (baud_counter < BAUD_COUNT) begin
                        baud_counter <= baud_counter + 1; // Contar hasta BAUD_COUNT
                    end else begin
                        ready <= 1;           // Indicar que los datos están listos
                        data_out <= data_reg; // Almacenar los datos recibidos
                        state <= IDLE;        // Regresar al estado inicial
                    end
                end
            endcase
        end
    end
endmodule

Proyecto/src/BT/BTr-testb.v
`include "BTr.v"  // Incluir el módulo de recepción BTr
`timescale 1ns / 1ps

// Testbench para el módulo BTr
module BTr_tb;

    // Parámetros
    parameter CLK_PERIOD = 20; // Período del reloj en ns (50MHz)

    // Señales de prueba
    reg clk;                     // Señal de reloj
    reg reset;                   // Señal de reset
    reg rx;                      // Entrada de recepción
    wire [7:0] data_out;        // Datos recibidos
    wire ready;                 // Indica que los datos están listos

    // Instanciar el módulo BTr
    BTr btr_inst (
        .clk(clk),
        .reset(reset),
        .rx(rx),
        .data_out(data_out),
        .ready(ready)
    );

    // Generar señal de reloj
    initial begin
        clk = 0;
        forever #(CLK_PERIOD / 2) clk = ~clk; // Cambiar el estado del reloj
    end

    // Proceso de prueba
    initial begin
        // Inicializar señales
        reset = 1;       // Activa el reset
        rx = 1;          // Mantener rx en alto inicialmente
        #(CLK_PERIOD);   // Esperar un ciclo de reloj
        reset = 0;       // Desactivar el reset

        // Esperar hasta que el módulo esté listo
        #(CLK_PERIOD * 10); // Esperar 10 ciclos de reloj

        // Simulación de recepción de un byte
        // Enviando el byte 0b10101010 (0xAA) a través de rx
        rx = 0;          // Bit de inicio
        #(CLK_PERIOD * 16); // Esperar 16 ciclos de reloj
        rx = 0;          // Bit 0
        #(CLK_PERIOD);   // Esperar 1 ciclo de reloj
        rx = 1;          // Bit 1
        #(CLK_PERIOD);   // Esperar 1 ciclo de reloj
        rx = 0;          // Bit 2
        #(CLK_PERIOD);   // Esperar 1 ciclo de reloj
        rx = 1;          // Bit 3
        #(CLK_PERIOD);   // Esperar 1 ciclo de reloj
        rx = 0;          // Bit 4
        #(CLK_PERIOD);   // Esperar 1 ciclo de reloj
        rx = 1;          // Bit 5
        #(CLK_PERIOD);   // Esperar 1 ciclo de reloj
        rx = 0;          // Bit 6
        #(CLK_PERIOD);   // Esperar 1 ciclo de reloj
        rx = 1;          // Bit 7
        #(CLK_PERIOD);   // Esperar 1 ciclo de reloj
        rx = 1;          // Bit de parada

        // Esperar un poco para verificar la salida
        #(CLK_PERIOD * 20); // Esperar 20 ciclos de reloj

        // Verificar datos recibidos
        if (data_out == 8'hAA && ready) begin
            $display("Datos recibidos correctamente: %b", data_out);
        end else begin
            $display("Error en la recepción de datos.");
        end

        // Finalizar simulación
        $finish;
    end

    // Generar archivo .vcd para GTKWave
    initial begin
        $dumpfile("BTr_tb.vcd"); // Nombre del archivo .vcd
        $dumpvars(0, BTr_tb);     // Registrar todas las variables del testbench
    end
endmodule

Proyecto/src/BT/BTr_tb.vcd
$date
	Mon Sep 23 18:31:14 2024
$end
$version
	Icarus Verilog
$end
$timescale
	1ps
$end
$scope module BTr_tb $end
$var wire 1 ! ready $end
$var wire 8 " data_out [7:0] $end
$var parameter 32 # CLK_PERIOD $end
$var reg 1 $ clk $end
$var reg 1 % reset $end
$var reg 1 & rx $end
$scope module btr_inst $end
$var wire 1 $ clk $end
$var wire 1 % reset $end
$var wire 1 & rx $end
$var parameter 65 ' BAUD_COUNT $end
$var parameter 32 ( BAUD_RATE $end
$var parameter 32 ) CLK_FREQ $end
$var parameter 2 * IDLE $end
$var parameter 2 + RECEIVE_DATA $end
$var parameter 2 , RECEIVE_START $end
$var parameter 2 - RECEIVE_STOP $end
$var reg 16 . baud_counter [15:0] $end
$var reg 4 / bit_index [3:0] $end
$var reg 8 0 data_out [7:0] $end
$var reg 8 1 data_reg [7:0] $end
$var reg 1 ! ready $end
$var reg 2 2 state [1:0] $end
$upscope $end
$upscope $end
$enddefinitions $end
$comment Show the parameter values. $end
$dumpall
b11 -
b1 ,
b10 +
b0 *
b10111110101111000010000000 )
b10010110000000 (
b101000100 '
b10100 #
$end
#0
$dumpvars
b0 2
bx 1
b0 0
b0 /
b0 .
1&
1%
0$
b0 "
0!
$end
#10000
1$
#20000
0$
0%
#30000
1$
#40000
0$
#50000
1$
#60000
0$
#70000
1$
#80000
0$
#90000
1$
#100000
0$
#110000
1$
#120000
0$
#130000
1$
#140000
0$
#150000
1$
#160000
0$
#170000
1$
#180000
0$
#190000
1$
#200000
0$
#210000
1$
#220000
0$
0&
#230000
b1 2
1$
#240000
0$
#250000
b1 .
1$
#260000
0$
#270000
b10 .
1$
#280000
0$
#290000
b11 .
1$
#300000
0$
#310000
b100 .
1$
#320000
0$
#330000
b101 .
1$
#340000
0$
#350000
b110 .
1$
#360000
0$
#370000
b111 .
1$
#380000
0$
#390000
b1000 .
1$
#400000
0$
#410000
b1001 .
1$
#420000
0$
#430000
b1010 .
1$
#440000
0$
#450000
b1011 .
1$
#460000
0$
#470000
b1100 .
1$
#480000
0$
#490000
b1101 .
1$
#500000
0$
#510000
b1110 .
1$
#520000
0$
#530000
b1111 .
1$
#540000
0$
#550000
b10000 .
1$
#560000
0$
1&
#570000
b10001 .
1$
#580000
0$
0&
#590000
b10010 .
1$
#600000
0$
1&
#610000
b10011 .
1$
#620000
0$
0&
#630000
b10100 .
1$
#640000
0$
1&
#650000
b10101 .
1$
#660000
0$
0&
#670000
b10110 .
1$
#680000
0$
1&
#690000
b10111 .
1$
#700000
0$
#710000
b11000 .
1$
#720000
0$
#730000
b11001 .
1$
#740000
0$
#750000
b11010 .
1$
#760000
0$
#770000
b11011 .
1$
#780000
0$
#790000
b11100 .
1$
#800000
0$
#810000
b11101 .
1$
#820000
0$
#830000
b11110 .
1$
#840000
0$
#850000
b11111 .
1$
#860000
0$
#870000
b100000 .
1$
#880000
0$
#890000
b100001 .
1$
#900000
0$
#910000
b100010 .
1$
#920000
0$
#930000
b100011 .
1$
#940000
0$
#950000
b100100 .
1$
#960000
0$
#970000
b100101 .
1$
#980000
0$
#990000
b100110 .
1$
#1000000
0$
#1010000
b100111 .
1$
#1020000
0$
#1030000
b101000 .
1$
#1040000
0$
#1050000
b101001 .
1$
#1060000
0$
#1070000
b101010 .
1$
#1080000
0$
#1090000
b101011 .
1$
